{
  "account": "@truth_nagaoka",
  "updated_at": "2026-07-21 07:59",
  "total_posts": 200,
  "total_likes": 20,
  "total_views": 21962,
  "total_replies": 16,
  "avg_likes": 0.1,
  "avg_views": 109.81,
  "recent_7days_count": 200,
  "recent_7days_avg_likes": 0.1,
  "top10_by_likes": [
    {
      "text": "週に何度も頭痛薬を飲んでいませんか？\n\n薬は一時しのぎ。\n睡眠不足を根本から変えると、\n頭痛の頻度が下がります。",
      "likes": 2,
      "views": 364,
      "replies": 0,
      "date": "2026-07-20"
    },
    {
      "text": "血管を収縮させ、頭痛を招きます。\n\n朝食にタンパク質を一品加えるだけで、\n午後の頭痛が変わります。",
      "likes": 2,
      "views": 1015,
      "replies": 0,
      "date": "2026-07-19"
    },
    {
      "text": "長岡市で１番健康情報を発信している整体院ですが\n実際に来院されるとこんな感じです。",
      "likes": 2,
      "views": 29,
      "replies": 0,
      "date": "2026-07-18"
    },
    {
      "text": "ご紹介ありがとうございます😊",
      "likes": 2,
      "views": 20,
      "replies": 1,
      "date": "2026-07-17"
    },
    {
      "text": "夜中に目が覚めるのは「歳のせい」じゃない。\n体が助けを求めているサインです\n無視しないで",
      "likes": 1,
      "views": 176,
      "replies": 0,
      "date": "2026-07-20"
    },
    {
      "text": "ストレス溜め込んで歯を食いしばってる人、\nこめかみ頭痛に直行してます。\n無意識にやってたら要注意。",
      "likes": 1,
      "views": 170,
      "replies": 0,
      "date": "2026-07-20"
    },
    {
      "text": "右肩が重い人は肝臓ケア。\n油ものを減らしてみて",
      "likes": 1,
      "views": 1237,
      "replies": 0,
      "date": "2026-07-19"
    },
    {
      "text": "呼吸の浅さの裏にある口呼吸、意識したことありますか。\n来院初日に「そこが原因だったのか」と驚く方が多いです。\n長岡市の整体院でも同じ相談が多いです。\n施術実績、",
      "likes": 1,
      "views": 59,
      "replies": 0,
      "date": "2026-07-19"
    },
    {
      "text": "頭痛があると、\n朝の時間の使い方が半減しますよね。\n\n根本から改善した方が\n長い目でみてずっと楽です。",
      "likes": 1,
      "views": 1,
      "replies": 0,
      "date": "2026-07-18"
    },
    {
      "text": "当院は長岡市で兄妹でやってますが\nたまに夫婦に間違えられます。\n\n兄妹です。",
      "likes": 1,
      "views": 62,
      "replies": 0,
      "date": "2026-07-18"
    }
  ],
  "top10_by_views": [
    {
      "text": "実は、長時間の座りっぱなしが \n筋肉を固め、血流を悪化させ、 \n朝のだるさや目の疲れにも \nつながっているんだ。",
      "views": 1786,
      "likes": 0,
      "date": "2026-07-17"
    },
    {
      "text": "右肩が重い人は肝臓ケア。\n油ものを減らしてみて",
      "views": 1237,
      "likes": 1,
      "date": "2026-07-19"
    },
    {
      "text": "血管を収縮させ、頭痛を招きます。\n\n朝食にタンパク質を一品加えるだけで、\n午後の頭痛が変わります。",
      "views": 1015,
      "likes": 2,
      "date": "2026-07-19"
    },
    {
      "text": "肩こり・頭痛に悩む人の共通点。\nそれは「圧倒的な水分不足」です",
      "views": 680,
      "likes": 0,
      "date": "2026-07-19"
    },
    {
      "text": "週に何度も頭痛薬を飲んでいませんか？\n\n薬は一時しのぎ。\n睡眠不足を根本から変えると、\n頭痛の頻度が下がります。",
      "views": 644,
      "likes": 0,
      "date": "2026-07-18"
    },
    {
      "text": "「天気が悪いと頭が痛い…」\nそれ、体内の水分バランスの乱れが原因かも\nカリウム豊富なバナナを試してみて",
      "views": 572,
      "likes": 0,
      "date": "2026-07-20"
    },
    {
      "text": "「偏頭痛の9割は水不足！？」 \n体重×30mlの水、今すぐ飲まないと危険かも…",
      "views": 502,
      "likes": 0,
      "date": "2026-07-18"
    },
    {
      "text": "天気が悪いと頭が痛い…\nそれ、気のせいじゃありません。\n\n気圧の低下で血管が拡張し、神経を圧迫しているサイン\n耳を温めると、血行が促進されて楽になりますよ",
      "views": 448,
      "likes": 0,
      "date": "2026-07-20"
    },
    {
      "text": "夜中に目が覚めるのは「歳のせい」じゃない。\n体が助けを求めているサインです\n無視しないで",
      "views": 419,
      "likes": 1,
      "date": "2026-07-17"
    },
    {
      "text": "当院は長岡市で兄妹でやってますが\nたまに夫婦に間違えられます。\n\n兄妹です。",
      "views": 395,
      "likes": 0,
      "date": "2026-07-20"
    }
  ],
  "worst10_by_views": [
    {
      "text": "「このくらいで整体に行っていいのか」と迷っている段階こそ来どきです。\n睡眠不足が浅いうちなら来院3〜5回で変わります。",
      "views": 2,
      "date": "2026-07-19"
    },
    {
      "text": "知らないうちに、歯を食いしばっていませんか？\nストレスが原因で、顎から首にかけての\n筋肉がガチガチに\n\nそれが、こめかみのズキズキに\n繋がっているかも",
      "views": 2,
      "date": "2026-07-18"
    },
    {
      "text": "その頭痛、揉んで治るタイプですか。冷やすタイプですか。\n間違った対処は逆効果になることもあります。\n60秒の無料診断で確かめられます👇\nhttps://trut",
      "views": 2,
      "date": "2026-07-18"
    },
    {
      "text": "「この頭痛、いつまで続くんだろう」と思ったらLINEへ。\n1週間で頭痛がラクになるセルフケア講座が、無料で毎日1通届きます👇\nhttps://lin.ee/qb",
      "views": 2,
      "date": "2026-07-18"
    },
    {
      "text": "寝かしつけで添い寝してたら首が固まる…\n\nそんな時は首の後ろのくぼみを\n親指でゆっくり押してみてください\n\nモヤモヤがスーッと消えていきます。",
      "views": 1,
      "date": "2026-07-19"
    },
    {
      "text": "首こりの本当の原因、知ってますか？",
      "views": 1,
      "date": "2026-07-19"
    },
    {
      "text": "頭痛があると、\n朝の時間の使い方が半減しますよね。\n\n根本から改善した方が\n長い目でみてずっと楽です。",
      "views": 1,
      "date": "2026-07-18"
    },
    {
      "text": "自律神経が乱れると、\n筋肉が常に緊張した状態になります。\n\n深呼吸を1日3回するだけで、\n身体の緊張がほぐれていきます。",
      "views": 1,
      "date": "2026-07-17"
    },
    {
      "text": "「水分不足」も頭痛の原因です。\n脳は80%が水分\n毎日1.5〜2L、こまめに飲んでいますか？",
      "views": 0,
      "date": "2026-07-20"
    },
    {
      "text": "頭の重さがひどい人に共通していること\n\n運動不足が主な原因です。\n施術だけでなく、日常の習慣を変えることが大切。",
      "views": 0,
      "date": "2026-07-19"
    }
  ],
  "performance_by_length": {
    "〜50字": {
      "count": 60,
      "avg_likes": 0.23,
      "avg_views": 151.6
    },
    "50〜100字": {
      "count": 119,
      "avg_likes": 0.05,
      "avg_views": 103.82
    },
    "100〜150字": {
      "count": 20,
      "avg_likes": 0.0,
      "avg_views": 23.95
    },
    "150字以上": {
      "count": 1,
      "avg_likes": 0.0,
      "avg_views": 32.0
    }
  }
}