{
  "account": "@masahide_takahashi_",
  "updated_at": "2026-04-29 07:55",
  "total_posts": 200,
  "total_likes": 0,
  "total_views": 0,
  "total_replies": 0,
  "avg_likes": 0.0,
  "avg_views": 0.0,
  "recent_7days_count": 200,
  "recent_7days_avg_likes": 0.0,
  "top10_by_likes": [
    {
      "text": "集客できない人がやりがちな\n5つの間違いを解説します。",
      "likes": 0,
      "views": 0,
      "replies": 0,
      "date": "2026-04-28"
    },
    {
      "text": "「Instagram集客、何から始めればいい？」\nそんな方はLINEに登録してみてください。\n\n一緒に整理しましょう。\n👉",
      "likes": 0,
      "views": 0,
      "replies": 0,
      "date": "2026-04-28"
    },
    {
      "text": "ショート動画制作で結果が出ない人の共通点。",
      "likes": 0,
      "views": 0,
      "replies": 0,
      "date": "2026-04-28"
    },
    {
      "text": "AIツールの使い分けで結果が出ない人の共通点。",
      "likes": 0,
      "views": 0,
      "replies": 0,
      "date": "2026-04-28"
    },
    {
      "text": "AIツールの使い分けで大切な3つのこと。",
      "likes": 0,
      "views": 0,
      "replies": 0,
      "date": "2026-04-28"
    },
    {
      "text": "AIコンテンツカレンダーで悩んでいる方、\nLINEで気軽に相談してください。",
      "likes": 0,
      "views": 0,
      "replies": 0,
      "date": "2026-04-28"
    },
    {
      "text": "TikTok集客で悩んでいる方、\nLINEで気軽に相談してください。",
      "likes": 0,
      "views": 0,
      "replies": 0,
      "date": "2026-04-28"
    },
    {
      "text": "広告費をかけなくても集客できます。\n\nなぜなら信頼を先に積み上げれば\nお客様は自然に来るから。",
      "likes": 0,
      "views": 0,
      "replies": 0,
      "date": "2026-04-28"
    },
    {
      "text": "教育コンテンツの作り方で結果を出す人がやっている\n3つの習慣をお伝えします。",
      "likes": 0,
      "views": 0,
      "replies": 0,
      "date": "2026-04-28"
    },
    {
      "text": "売れるAIコンテンツカレンダーと売れないAIコンテンツカレンダーの違い。",
      "likes": 0,
      "views": 0,
      "replies": 0,
      "date": "2026-04-28"
    }
  ],
  "performance_by_length": {
    "〜50字": {
      "count": 141,
      "avg_likes": 0.0,
      "avg_views": 0.0
    },
    "50〜100字": {
      "count": 46,
      "avg_likes": 0.0,
      "avg_views": 0.0
    },
    "100〜150字": {
      "count": 6,
      "avg_likes": 0.0,
      "avg_views": 0.0
    },
    "150字以上": {
      "count": 7,
      "avg_likes": 0.0,
      "avg_views": 0.0
    }
  }
}