{
  "account": "@truth_nagaoka",
  "updated_at": "2026-05-18 07:51",
  "total_posts": 200,
  "total_likes": 0,
  "total_views": 0,
  "total_replies": 0,
  "avg_likes": 0.0,
  "avg_views": 0.0,
  "recent_7days_count": 200,
  "recent_7days_avg_likes": 0.0,
  "top10_by_likes": [
    {
      "text": "「頭の重さくらいで整体は大げさ」",
      "likes": 0,
      "views": 0,
      "replies": 0,
      "date": "2026-05-17"
    },
    {
      "text": "天気が悪いと頭が痛い…\nそれ、気のせいじゃありません。\n\n気圧の低下で血管が拡張し、神経を圧迫しているサイン\n耳を温めると、血行が促進されて楽になりますよ",
      "likes": 0,
      "views": 0,
      "replies": 0,
      "date": "2026-05-17"
    },
    {
      "text": "「水分は足りてる」って言って、\nコーヒーばっかり飲んでませんか？\n\n水を飲まないと頭痛は改善しません。",
      "likes": 0,
      "views": 0,
      "replies": 0,
      "date": "2026-05-17"
    },
    {
      "text": "呼吸の浅さを悪化させる習慣 TOP3\n\n1位：食いしばりがある\n2位：肩が内側に入っている\n3位：運動習慣がない\n\n心当たりある人、多いはず。",
      "likes": 0,
      "views": 0,
      "replies": 0,
      "date": "2026-05-17"
    },
    {
      "text": "胃の不調、食べ過ぎじゃなく「背中の張り」が原因かも。\n背中の自律神経は胃の働きをコントロールしています。\n背中がガチガチだと自律神経が乱れ、\n胃の機能が低下して",
      "likes": 0,
      "views": 0,
      "replies": 0,
      "date": "2026-05-17"
    },
    {
      "text": "実は当院って見附市や津南町、柏崎市\n南魚沼市、三条市からも\n来院されてます。",
      "likes": 0,
      "views": 0,
      "replies": 0,
      "date": "2026-05-17"
    },
    {
      "text": "自律神経が乱れると、\n筋肉が常に緊張した状態になります。\n\n深呼吸を1日3回するだけで、\n身体の緊張がほぐれていきます。",
      "likes": 0,
      "views": 0,
      "replies": 0,
      "date": "2026-05-17"
    },
    {
      "text": "睡眠と頭痛は直結している。\n眠れないから頭が痛い、頭が痛いから眠れない\nこの悪循環、断ち切れます",
      "likes": 0,
      "views": 0,
      "replies": 0,
      "date": "2026-05-17"
    },
    {
      "text": "頭痛があると、\n朝の時間の使い方が半減しますよね。\n\n根本から改善した方が\n長い目でみてずっと楽です。",
      "likes": 0,
      "views": 0,
      "replies": 0,
      "date": "2026-05-17"
    },
    {
      "text": "頭痛を放っておくと「薬が手放せない生活」に。\n毎日飲んでいるなら、もう慢性頭痛のサインです。",
      "likes": 0,
      "views": 0,
      "replies": 0,
      "date": "2026-05-17"
    }
  ],
  "performance_by_length": {
    "〜50字": {
      "count": 153,
      "avg_likes": 0.0,
      "avg_views": 0.0
    },
    "50〜100字": {
      "count": 45,
      "avg_likes": 0.0,
      "avg_views": 0.0
    },
    "100〜150字": {
      "count": 2,
      "avg_likes": 0.0,
      "avg_views": 0.0
    }
  }
}